plating/__init__.py
plating/_version.py
plating/async_template_engine.py
plating/cli.py
plating/decorators.py
plating/error_handling.py
plating/errors.py
plating/example_compiler.py
plating/linting.py
plating/markdown_validator.py
plating/models.py
plating/plating.py
plating/registry.py
plating/schema.py
plating/template_filters.py
plating/template_functions.py
plating/templates.py
plating/types.py
plating/adorner/__init__.py
plating/adorner/adorner.py
plating/adorner/api.py
plating/adorner/finder.py
plating/adorner/templates.py
plating/bundles/__init__.py
plating/bundles/base.py
plating/bundles/function.py
plating/config/__init__.py
plating/config/defaults.py
plating/config/runtime.py
plating/core/__init__.py
plating/core/doc_generator.py
plating/core/project_utils.py
plating/core/schema_helpers.py
plating/discovery/__init__.py
plating/discovery/finder.py
plating/discovery/templates.py
plating/generation/__init__.py
plating/generation/adorner.py
plating/generation/plater.py
plating/generation/renderer.py
plating/schema_utils/__init__.py
plating/schema_utils/formatters.py
plating-0.0.1000.post0.dist-info/licenses/LICENSE
plating-0.0.1000.post0.dist-info/METADATA
plating-0.0.1000.post0.dist-info/WHEEL
plating-0.0.1000.post0.dist-info/entry_points.txt
plating-0.0.1000.post0.dist-info/top_level.txt
plating-0.0.1000.post0.dist-info/RECORD
