Metadata-Version: 2.4
Name: plating
Version: 0.0.1000.post0
Summary: Documentation generation system for Terraform/OpenTofu providers
Author-email: Tim Perkins <code@tim.life>
Maintainer-email: "provide.io" <code@provide.io>
License-Expression: Apache-2.0
Classifier: Development Status :: 3 - Alpha
Classifier: Intended Audience :: Developers
Classifier: Operating System :: OS Independent
Classifier: Programming Language :: Python :: 3
Classifier: Programming Language :: Python :: 3.11
Classifier: Programming Language :: Python :: 3.12
Classifier: Programming Language :: Python :: 3.13
Classifier: Typing :: Typed
Requires-Python: >=3.11
License-File: LICENSE
Requires-Dist: jinja2<4.0.0,>=3.1.6
Requires-Dist: rich<14.0.0,>=13.0.0
Requires-Dist: pyvider-cty>=0.0.1000
Requires-Dist: provide-foundation[all]>=0.0.1000
Requires-Dist: pymarkdownlnt>=0.9.32
Requires-Dist: mkdocs-material>=9.6.20
Dynamic: license-file
